_echopype_version.py
echopype/__init__.py
echopype/core.py
echopype/testing.py
echopype/calibrate/__init__.py
echopype/calibrate/api.py
echopype/calibrate/cal_params.py
echopype/calibrate/calibrate_azfp.py
echopype/calibrate/calibrate_base.py
echopype/calibrate/calibrate_ek.py
echopype/calibrate/ecs.py
echopype/calibrate/ek80_complex.py
echopype/calibrate/env_params.py
echopype/calibrate/env_params_old.py
echopype/calibrate/range.py
echopype/clean/__init__.py
echopype/clean/api.py
echopype/clean/utils.py
echopype/clean/transient_noise/transient_fielding.py
echopype/clean/transient_noise/transient_matecho.py
echopype/colormap/__init__.py
echopype/colormap/cm.py
echopype/commongrid/__init__.py
echopype/commongrid/api.py
echopype/commongrid/utils.py
echopype/consolidate/__init__.py
echopype/consolidate/api.py
echopype/consolidate/ek_depth_utils.py
echopype/consolidate/loc_utils.py
echopype/consolidate/split_beam_angle.py
echopype/convert/__init__.py
echopype/convert/ad2cp_fields.yaml
echopype/convert/api.py
echopype/convert/parse_ad2cp.py
echopype/convert/parse_azfp.py
echopype/convert/parse_azfp6.py
echopype/convert/parse_base.py
echopype/convert/parse_ek60.py
echopype/convert/parse_ek80.py
echopype/convert/set_groups_ad2cp.py
echopype/convert/set_groups_azfp.py
echopype/convert/set_groups_azfp6.py
echopype/convert/set_groups_base.py
echopype/convert/set_groups_ek60.py
echopype/convert/set_groups_ek80.py
echopype/convert/utils/__init__.py
echopype/convert/utils/ek_date_conversion.py
echopype/convert/utils/ek_duplicates.py
echopype/convert/utils/ek_raw_io.py
echopype/convert/utils/ek_raw_parsers.py
echopype/convert/utils/ek_swap.py
echopype/echodata/__init__.py
echopype/echodata/api.py
echopype/echodata/combine.py
echopype/echodata/echodata.py
echopype/echodata/simrad.py
echopype/echodata/utils_platform.py
echopype/echodata/convention/1.0.yml
echopype/echodata/convention/__init__.py
echopype/echodata/convention/conv.py
echopype/echodata/convention/utils.py
echopype-0.11.0.dist-info/licenses/LICENSE
echopype-0.11.0.dist-info/METADATA
echopype-0.11.0.dist-info/WHEEL
echopype-0.11.0.dist-info/top_level.txt
echopype-0.11.0.dist-info/RECORD
