Metadata-Version: 2.4
Name: echopype
Version: 0.11.0
Summary: Enhancing the interoperability and scalability in analyzing ocean sonar data
Home-page: https://github.com/OSOceanAcoustics/echopype
Author: Wu-Jung Lee
Author-email: leewujung@gmail.com
Maintainer: Wu-Jung Lee
Maintainer-email: leewujung@gmail.com
License: Apache License, Version 2.0
Platform: OS Independent
Classifier: Development Status :: 4 - Beta
Classifier: Environment :: Console
Classifier: Intended Audience :: Science/Research
Classifier: License :: OSI Approved :: Apache Software License
Classifier: Operating System :: OS Independent
Classifier: Programming Language :: Python
Classifier: Programming Language :: Python :: 3 :: Only
Classifier: Programming Language :: Python :: 3.11
Classifier: Programming Language :: Python :: 3.12
Classifier: Programming Language :: Python :: 3.13
Classifier: Topic :: Scientific/Engineering
Requires-Python: <3.14,>=3.9
License-File: LICENSE
Requires-Dist: aiohttp
Requires-Dist: bottleneck
Requires-Dist: dask[array,distributed]
Requires-Dist: dask-image
Requires-Dist: flox>=0.7.2
Requires-Dist: fsspec
Requires-Dist: geopy
Requires-Dist: jinja2
Requires-Dist: netCDF4>1.6
Requires-Dist: numpy
Requires-Dist: pandas
Requires-Dist: psutil>=5.9.1
Requires-Dist: pynmea2
Requires-Dist: pytz
Requires-Dist: requests
Requires-Dist: s3fs
Requires-Dist: scipy
Requires-Dist: typing-extensions
Requires-Dist: xarray>=2024.11.0
Requires-Dist: zarr>=3
Provides-Extra: plot
Requires-Dist: matplotlib>=3.7; extra == "plot"
Requires-Dist: cmocean; extra == "plot"
Dynamic: license-file
Dynamic: requires-dist
